[{"Argentina":{"items":[{"NAME":"Belgrano I","TYPE":"Station","LAT":-79,"LON":-40},{"NAME":"Belgrano II Antarctic Base","TYPE":"Station","LAT":-77.87388899999999,"LON":-34.627778},{"NAME":"Belgrano III","TYPE":"Station","LAT":null,"LON":null},{"NAME":"Brown Antarctic Base","TYPE":"Station","LAT":-64.89537,"LON":-62.870452},{"NAME":"Cámara Antarctic Base","TYPE":"Station","LAT":-62.593858000000004,"LON":-59.919343999999995},{"NAME":"Carlini Antarctic Base","TYPE":"Station","LAT":-62.2379,"LON":-58.666841999999995},{"NAME":"Decepción Antarctic Base","TYPE":"Station","LAT":-62.97676,"LON":-60.700695},{"NAME":"Ellsworth","TYPE":"Station","LAT":null,"LON":null},{"NAME":"Esperanza Antarctic Base","TYPE":"Station","LAT":-63.396959,"LON":-56.998054},{"NAME":"Marambio Antarctic Base","TYPE":"Station","LAT":-64.241769,"LON":-56.623225},{"NAME":"Matienzo Antarctic Base","TYPE":"Station","LAT":-64.975865,"LON":-60.070948},{"NAME":"Melchior Antarctic Base","TYPE":"Station","LAT":-64.325705,"LON":-62.976329},{"NAME":"Orcadas","TYPE":"Station","LAT":-60.737592,"LON":-44.737387},{"NAME":"Petrel Antarctic Base","TYPE":"Station","LAT":-63.478303000000004,"LON":-56.230993000000005},{"NAME":"Primavera","TYPE":"Station","LAT":-64.155854,"LON":-60.954256},{"NAME":"San Martín Antarctic Base","TYPE":"Station","LAT":-68.13029999999999,"LON":-67.102931},{"NAME":"Sobral","TYPE":"Station","LAT":-81.83305555555555,"LON":-40.65},{"NAME":"17 de agosto","TYPE":"Refuge","LAT":-68.12972222222221,"LON":-67.2238888888889},{"NAME":"Ballvé","TYPE":"Refuge","LAT":-62.21666666666667,"LON":-58.88333333333333},{"NAME":"Cobbett","TYPE":"Refuge","LAT":-64.155854,"LON":-60.954256},{"NAME":"Conscripto Ortiz","TYPE":"Refuge","LAT":-64.89537,"LON":-62.870452},{"NAME":"Cristo Redentor","TYPE":"Refuge","LAT":-63.55361111111111,"LON":-57.37888888888889},{"NAME":"Elefante","TYPE":"Refuge","LAT":-62.25472222222222,"LON":-58.632222222222225},{"NAME":"Francisco de Gurruchaga","TYPE":"Refuge","LAT":-62.31666666666667,"LON":-59.15},{"NAME":"Independencia Argentina","TYPE":"Refuge","LAT":-63.46,"LON":-57.18722222222222},{"NAME":"Islas Malvinas","TYPE":"Refuge","LAT":-63.419444444444444,"LON":-56.99722222222222},{"NAME":"Martín Güemes","TYPE":"Refuge","LAT":-63.475,"LON":-57.065},{"NAME":"Ona","TYPE":"Refuge","LAT":-68.10055555555554,"LON":-67.02555555555556},{"NAME":"Sarg Ayte Cisterna","TYPE":"Refuge","LAT":-77.88222222222221,"LON":-34.31527777777777},{"NAME":"Suecia","TYPE":"Refuge","LAT":-64.46666666666667,"LON":-57.2},{"NAME":"Dallmann","TYPE":"Laboratory","LAT":-62.237609,"LON":-58.666716},{"NAME":"Estación climatológica Lachman","TYPE":"Automatic Recording Station","LAT":-63.884166666666665,"LON":-57.801111111111105},{"NAME":"Estación de Monitoreo de Permafrost (Marambio VOR)","TYPE":"Automatic Recording Station","LAT":-64.245,"LON":-56.65694444444444},{"NAME":"Estación de Monitoreo de Permafrost (Riscos Rink)","TYPE":"Automatic Recording Station","LAT":-63.903888888888886,"LON":-58.21222222222222},{"NAME":"Estación de Monitoreo de Permafrost Lachman Costa","TYPE":"Automatic Recording Station","LAT":-63.871944444444445,"LON":-57.77777777777778},{"NAME":"Estación de monitoreo de permafrost Lachman Hornfels","TYPE":"Automatic Recording Station","LAT":-63.87222222222222,"LON":-57.78583333333333},{"NAME":"Estación de Monitoreo de Permafrost Riscos Tumbledown","TYPE":"Automatic Recording Station","LAT":-64.06944444444444,"LON":-58.41277777777778},{"NAME":"Estación Mareográfica de Nueva Generación (NQWLMS)","TYPE":"Automatic Recording Station","LAT":-62.4,"LON":-57},{"NAME":"Estación sismológica en Base Carlini (ex Jubany)","TYPE":"Automatic Recording Station","LAT":-62.23777777777778,"LON":-58.66444444444444},{"NAME":"Laboratorio Antártico Multidisciplinario (LABEL) en Base Belgrano II","TYPE":"Automatic Recording Station","LAT":-77.87083333333332,"LON":-34.62777777777778},{"NAME":"Laboratorio Antártico Multidisciplinario (LABES), en Base Esperanza","TYPE":"Automatic Recording Station","LAT":-63.394999999999996,"LON":-56.99611111111111},{"NAME":"Laboratorio Antártico Multidisciplinario (LABOR) en Base Orcadas","TYPE":"Automatic Recording Station","LAT":-60.75,"LON":-44.71666666666667},{"NAME":"Laboratorio Antártico Multidisciplinario (LAJUB) en Base Carlini (ex Jubany)","TYPE":"Automatic Recording Station","LAT":-62.23777777777778,"LON":-58.66444444444444},{"NAME":"Laboratorio Antártico Multidisciplinario (LAMBI), en Base Marambio","TYPE":"Automatic Recording Station","LAT":-64.245,"LON":-56.65694444444444},{"NAME":"Laboratorio Antártico Multidisciplinario (LASAN) en Base San Martín","TYPE":"Automatic Recording Station","LAT":-68.12944444444443,"LON":-67.10305555555556},{"NAME":"Laboratorio Dallmann en Base Carlini (ex Jubany)","TYPE":"Automatic Recording Station","LAT":-62.23777777777778,"LON":-58.66444444444444},{"NAME":"Matienzo","TYPE":"Automatic Recording Station","LAT":-64.98333333333333,"LON":-60.11666666666667},{"NAME":"Vega, isla","TYPE":"Automatic Recording Station","LAT":-63.833333333333336,"LON":-57.36666666666667}],"color":"#74ACDF","code":"ar"}},{"Australia":{"items":[{"NAME":"Beaver Lake","TYPE":"Station","LAT":-70.79277777777777,"LON":68.29527777777777},{"NAME":"Cape Denison","TYPE":"Station","LAT":-67,"LON":142.66666666666666},{"NAME":"Casey","TYPE":"Station","LAT":-66.282343,"LON":110.526792},{"NAME":"Casey Area emergency depots","TYPE":"Station","LAT":null,"LON":null},{"NAME":"Davis","TYPE":"Station","LAT":-68.575938,"LON":77.969516},{"NAME":"Mawson","TYPE":"Station","LAT":-67.602644,"LON":62.873028},{"NAME":"Ace Lake Refuge","TYPE":"Refuge","LAT":-68.47166666666666,"LON":78.18777777777778},{"NAME":"Bandits Refuge","TYPE":"Refuge","LAT":-68.42166666666667,"LON":78.38472222222222},{"NAME":"Bechervaise Island Huts","TYPE":"Refuge","LAT":-67.58388888888888,"LON":62.801111111111105},{"NAME":"Brookes Refuge","TYPE":"Refuge","LAT":-68.60166666666666,"LON":78.18472222222222},{"NAME":"Browning Peninsula Refuge","TYPE":"Refuge","LAT":-66.46944444444445,"LON":110.55},{"NAME":"Colbeck Hut","TYPE":"Refuge","LAT":-67.41416666666667,"LON":61.005},{"NAME":"Crooked Lake Refuge and Boulder Tent Depot","TYPE":"Refuge","LAT":-68.61694444444444,"LON":78.38194444444444},{"NAME":"Fang Hut","TYPE":"Refuge","LAT":-67.79472222222222,"LON":62.58444444444444},{"NAME":"Jack´s Donga","TYPE":"Refuge","LAT":-66.21861111111112,"LON":110.65055555555556},{"NAME":"Law","TYPE":"Refuge","LAT":-69.38829600000001,"LON":76.380696},{"NAME":"Ledingham Depot","TYPE":"Refuge","LAT":-67.36666666666666,"LON":59.4525},{"NAME":"Macey Hut","TYPE":"Refuge","LAT":-67.43916666666667,"LON":63.81916666666667},{"NAME":"Marine Plain Refuge","TYPE":"Refuge","LAT":-68.60249999999999,"LON":78.10138888888888},{"NAME":"Mt Henderson Hut","TYPE":"Refuge","LAT":-67.70083333333334,"LON":63.05638888888888},{"NAME":"Peterson Island Emergency Shelter","TYPE":"Refuge","LAT":-66.46666666666667,"LON":110.5},{"NAME":"Platcha Refuge","TYPE":"Refuge","LAT":-68.51166666666667,"LON":78.51222222222222},{"NAME":"Rauer Islands Filla Refuge","TYPE":"Refuge","LAT":-68.80805555555555,"LON":77.85638888888889},{"NAME":"Rauer Islands Hop Refuge","TYPE":"Refuge","LAT":-68.8286111111111,"LON":77.70222222222222},{"NAME":"Robinson Ridge Refuge","TYPE":"Refuge","LAT":-66.36888888888888,"LON":110.59444444444443},{"NAME":"Rookery Lake Refuge","TYPE":"Refuge","LAT":-68.49805555555555,"LON":78.07305555555556},{"NAME":"Rumdoodle Hut","TYPE":"Refuge","LAT":-67.76888888888888,"LON":62.816944444444445},{"NAME":"Scullin Monolith Refuge","TYPE":"Refuge","LAT":-67.78333333333333,"LON":66.7},{"NAME":"Trajer Ridge Refuge","TYPE":"Refuge","LAT":-68.56083333333333,"LON":78.5},{"NAME":"Watts Lake Refuge","TYPE":"Refuge","LAT":-68.60333333333332,"LON":78.21944444444445},{"NAME":"Wilkes 'Hilton' Refuge","TYPE":"Refuge","LAT":-66.25722222222223,"LON":110.52555555555556},{"NAME":"Edgeworth David","TYPE":"Camp","LAT":-66.24993500000001,"LON":100.60421299999999},{"NAME":"Wilkins Aerodrome","TYPE":"Airfield Camp","LAT":-66.689167,"LON":111.483333},{"NAME":"Airstrip 2 - Casey","TYPE":"Automatic Recording Station","LAT":-66.27527777777777,"LON":110.79777777777778},{"NAME":"Cape Poinsett - Casey","TYPE":"Automatic Recording Station","LAT":-65.84472222222222,"LON":113.06666666666666},{"NAME":"Casey","TYPE":"Automatic Recording Station","LAT":-66.282343,"LON":110.526792},{"NAME":"Davis","TYPE":"Automatic Recording Station","LAT":-68.575938,"LON":77.969516},{"NAME":"Halfway - Casey","TYPE":"Automatic Recording Station","LAT":-66.66027777777778,"LON":112.01166666666667},{"NAME":"LGB00 - Mawson","TYPE":"Automatic Recording Station","LAT":-68.65527777777778,"LON":61.11277777777778},{"NAME":"LGB10 - Mawson","TYPE":"Automatic Recording Station","LAT":-71.2875,"LON":59.21027777777778},{"NAME":"LGB20 - Mawson","TYPE":"Automatic Recording Station","LAT":-73.83277777777778,"LON":55.67166666666667},{"NAME":"LGB35 Davis","TYPE":"Automatic Recording Station","LAT":-76.04388888888889,"LON":65.01666666666667},{"NAME":"LGB69 - Davis","TYPE":"Automatic Recording Station","LAT":-70.83527777777778,"LON":77.07444444444444},{"NAME":"Mawson","TYPE":"Automatic Recording Station","LAT":-67.602644,"LON":62.873028},{"NAME":"Mount Brown - Davis","TYPE":"Automatic Recording Station","LAT":-69.13111111111111,"LON":85.99916666666667},{"NAME":"Southern ocean","TYPE":"Automatic Recording Station","LAT":-70,"LON":150},{"NAME":"Upper Peterson Airfield - Casey","TYPE":"Automatic Recording Station","LAT":-66.69305555555556,"LON":111.5038888888889}],"color":"#00008B","code":"au"}},{"Belarus":{"items":[{"NAME":"Mountain Evening","TYPE":"Station","LAT":-67.65833333333335,"LON":46.15333333333333}],"color":"#C8102E","code":"by"}},{"Belgium":{"items":[{"NAME":"Princess Elisabeth Antarctica","TYPE":"Station","LAT":-71.949858,"LON":23.346891},{"NAME":"Princess Elisabeth Antarctica","TYPE":"Automatic Recording Station","LAT":-71.949858,"LON":23.346891}],"color":"#FCD116","code":"be"}},{"Brazil":{"items":[{"NAME":"Comandante Ferraz","TYPE":"Station","LAT":-62.08547166666667,"LON":-58.39872166666667},{"NAME":"Criosfera 1","TYPE":"Station","LAT":-84,"LON":-79.5},{"NAME":"Cruls","TYPE":"Refuge","LAT":-62.25,"LON":-58.975},{"NAME":"Engenheiro Wiltgen","TYPE":"Refuge","LAT":-61.21866666666667,"LON":-55.37},{"NAME":"Goeldi","TYPE":"Refuge","LAT":-61.13333333333333,"LON":-55.35},{"NAME":"Comandante Ferraz","TYPE":"Automatic Recording Station","LAT":-62.08547166666667,"LON":-58.39872166666667},{"NAME":"Criosfera 1 Station (Cryosphere 1)","TYPE":"Automatic Recording Station","LAT":-84,"LON":-79.49416666666667},{"NAME":"CRIOSFERA 2 (SkyBRA)","TYPE":"Automatic Recording Station","LAT":-79.69691666666667,"LON":-78.6765},{"NAME":"Joinville Island","TYPE":"Automatic Recording Station","LAT":-63.18805555555555,"LON":-55.39194444444444}],"color":"#009B3A","code":"br"}},{"Bulgaria":{"items":[],"color":"#00966E","code":"bg"}},{"Canada":{"items":[],"color":"#FF0000","code":"ca"}},{"Chile":{"items":[{"NAME":"Arturo Prat Antarctic Naval Base","TYPE":"Station","LAT":-62.478717,"LON":-59.663603},{"NAME":"Bahía Fildes Maritime Station","TYPE":"Station","LAT":-62.18333333333333,"LON":-58.916666666666664},{"NAME":"Carvajal","TYPE":"Station","LAT":-67.75,"LON":-68.9},{"NAME":"Dr. Guillermo Mann","TYPE":"Station","LAT":-62.470150000000004,"LON":-60.771178},{"NAME":"Estación Marítima Bahía Paraíso","TYPE":"Station","LAT":-64.82386199999999,"LON":-62.857499000000004},{"NAME":"Gabriel González Videla","TYPE":"Station","LAT":-64.82386199999999,"LON":-62.857499000000004},{"NAME":"Lieutenant Arturo Parodi","TYPE":"Station","LAT":-80.311933,"LON":-81.36657299999999},{"NAME":"O'Higgins Base","TYPE":"Station","LAT":-63.320951,"LON":-57.899781},{"NAME":"President Eduardo Frei Antarctic Base","TYPE":"Station","LAT":-62.200232,"LON":-58.962627000000005},{"NAME":"Profesor Julio Escudero","TYPE":"Station","LAT":-62.201373000000004,"LON":-58.962676},{"NAME":"Rada Covadonga","TYPE":"Station","LAT":-63.320951,"LON":-57.899781},{"NAME":"Risopatrón","TYPE":"Station","LAT":-62.378533,"LON":-59.700724},{"NAME":"Yelcho","TYPE":"Station","LAT":-64.875858,"LON":-63.583806},{"NAME":"11 de septiembre","TYPE":"Refuge","LAT":-63.60527777777778,"LON":-57.591944444444444},{"NAME":"Abrazo de Maipú","TYPE":"Refuge","LAT":-63.38333333333333,"LON":-57.56666666666667},{"NAME":"General Jorge Boonen Rivera (Ex- Gral. Ramón Cañas Montalva)","TYPE":"Refuge","LAT":-63.5375,"LON":-57.40416666666667},{"NAME":"Julio Ripamonti","TYPE":"Refuge","LAT":-62.21083333333333,"LON":-58.88527777777778},{"NAME":"Refugio Collins","TYPE":"Refuge","LAT":-62.166666666666664,"LON":-58.85},{"NAME":"Ripamonti","TYPE":"Refuge","LAT":-62.210151,"LON":-58.93474},{"NAME":"Estacion Polar Cientifica Conjunta Glaciar Union","TYPE":"Camp","LAT":-79.766667,"LON":-82.916667},{"NAME":"Lieutenant Rodolfo Marsh Martin Aerodrome","TYPE":"Airfield Camp","LAT":-62.193794,"LON":-58.980605000000004},{"NAME":"Dr. Guillermo Mann","TYPE":"Automatic Recording Station","LAT":-62.45,"LON":-60.78333333333333},{"NAME":"Gabriel González Videla","TYPE":"Automatic Recording Station","LAT":-64.81666666666666,"LON":-62.86666666666667},{"NAME":"General Bernardo O'Higgins","TYPE":"Automatic Recording Station","LAT":-63.32055555555556,"LON":-57.903055555555554},{"NAME":"Luis Risopatrón","TYPE":"Automatic Recording Station","LAT":-62.36666666666667,"LON":-59.65},{"NAME":"Presidente Eduardo Frei Montalva","TYPE":"Automatic Recording Station","LAT":-62.18333333333333,"LON":-58.983333333333334},{"NAME":"Profesor Julio Escudero","TYPE":"Automatic Recording Station","LAT":-62.2,"LON":-58.95},{"NAME":"Teniente Luis Carvajal Villarroel","TYPE":"Automatic Recording Station","LAT":-67.75,"LON":-68.9}],"color":"#0039A6","code":"cl"}},{"China":{"items":[{"NAME":"Great Wall","TYPE":"Station","LAT":-62.217519,"LON":-58.961992},{"NAME":"Kunlun","TYPE":"Station","LAT":-80.41719,"LON":77.115997},{"NAME":"Zhongshan","TYPE":"Station","LAT":-69.373206,"LON":76.371871},{"NAME":"Taishan","TYPE":"Camp","LAT":-73.86361111111111,"LON":76.9413888888889},{"NAME":"Eagle Camp","TYPE":"Automatic Recording Station","LAT":-76.41666666666667,"LON":77.01666666666667},{"NAME":"PANDA-South","TYPE":"Automatic Recording Station","LAT":-81.32416666666666,"LON":75.98805555555556},{"NAME":"CHNA","TYPE":"Automatic Recording Station","LAT":-78.67694444444444,"LON":77.01277777777777},{"NAME":"CHNB","TYPE":"Automatic Recording Station","LAT":-77.17444444444445,"LON":76.97611111111111},{"NAME":"Dome A","TYPE":"Automatic Recording Station","LAT":-80.42194444444445,"LON":77.10444444444444},{"NAME":"Dome A","TYPE":"Automatic Recording Station","LAT":-80.36666666666666,"LON":77.36666666666666},{"NAME":"DT154","TYPE":"Automatic Recording Station","LAT":-74.5825,"LON":77.02638888888889},{"NAME":"Eagle Camp","TYPE":"Automatic Recording Station","LAT":-76.41555555555556,"LON":77.04861111111111},{"NAME":"Great Wall","TYPE":"Automatic Recording Station","LAT":-62.217519,"LON":-58.961992},{"NAME":"Kunlun Station","TYPE":"Automatic Recording Station","LAT":-80.41694444444445,"LON":77.11611111111111},{"NAME":"LGB69Zhongshan","TYPE":"Automatic Recording Station","LAT":-70.83333333333333,"LON":77.06666666666666},{"NAME":"LT892","TYPE":"Automatic Recording Station","LAT":-71.67083333333333,"LON":77.76277777777777},{"NAME":"Zhongshan","TYPE":"Automatic Recording Station","LAT":-69.373206,"LON":76.371871},{"NAME":"Zhongshan","TYPE":"Automatic Recording Station","LAT":-69.38333333333334,"LON":76.38},{"NAME":"Zhongshan","TYPE":"Automatic Recording Station","LAT":-69.3711111111111,"LON":76.36972222222222}],"color":"#DE2910","code":"cn"}},{"Colombia":{"items":[],"color":"#FCD116","code":"co"}},{"Czechia":{"items":[{"NAME":"CZ*ECO Nelson","TYPE":"Station","LAT":-62.25,"LON":-58.983333333333334},{"NAME":"Johann Gregor Mendel","TYPE":"Station","LAT":-63.800625,"LON":-57.882592},{"NAME":"CZ*ECO Nelson","TYPE":"Automatic Recording Station","LAT":-62.25,"LON":-58.983333333333334},{"NAME":"Johann Gregor Mendel","TYPE":"Automatic Recording Station","LAT":-63.800625,"LON":-57.882592}],"color":"#11457E","code":"cz"}},{"Ecuador":{"items":[{"NAME":"Pedro Vicente Maldonado","TYPE":"Station","LAT":-62.449329999999996,"LON":-59.740968333333335},{"NAME":"República del Ecuador","TYPE":"Refuge","LAT":-62.12099,"LON":-58.395161}],"color":"#FCDD09","code":"ec"}},{"Finland":{"items":[{"NAME":"Aboa","TYPE":"Station","LAT":-73.042282,"LON":-13.407358},{"NAME":"Aboa","TYPE":"Automatic Recording Station","LAT":-73.042282,"LON":-13.407358}],"color":"#003580","code":"fi"}},{"France":{"items":[{"NAME":"Cap Prudhomme","TYPE":"Station","LAT":-66.687608,"LON":139.90717},{"NAME":"Concordia","TYPE":"Station","LAT":-75.099975,"LON":123.332605},{"NAME":"Dumont d'Urville","TYPE":"Station","LAT":-66.662833,"LON":140.001333},{"NAME":"Robert Guillard","TYPE":"Station","LAT":-66.687608,"LON":139.90717},{"NAME":"D85 Skiway camp","TYPE":"Airfield Camp","LAT":-70.42500000000001,"LON":134.14583299999998},{"NAME":"Concordia - dome C","TYPE":"Automatic Recording Station","LAT":-76.1,"LON":123.33333333333333},{"NAME":"Dumont d'Urville Station","TYPE":"Automatic Recording Station","LAT":-66.66277777777778,"LON":140.0013888888889}],"color":"#002395","code":"fr"}},{"Germany":{"items":[{"NAME":"Closed Facilities: Lillie Marleen Hut","TYPE":"Station","LAT":-71.2,"LON":164.51666666666668},{"NAME":"Closed Facilities: Neumayer Station II","TYPE":"Station","LAT":-70.65,"LON":-8.25},{"NAME":"German Antarctic Receiving Station (GARS)","TYPE":"Station","LAT":-63.321092,"LON":-57.90094},{"NAME":"Gondwana Station","TYPE":"Station","LAT":-74.635501,"LON":164.221215},{"NAME":"Kohnen","TYPE":"Station","LAT":-75.00190833333333,"LON":0.06633666666666667},{"NAME":"Neumayer III","TYPE":"Station","LAT":-70.66051666666667,"LON":-8.284148333333333},{"NAME":"Dallmann","TYPE":"Laboratory","LAT":-62.237609,"LON":-58.666716},{"NAME":"Georg Forster","TYPE":"Airfield Camp","LAT":-70.766667,"LON":11.683333},{"NAME":"Air Chemical Observatory at Neumayer Station III","TYPE":"Automatic Recording Station","LAT":-70.66666666666667,"LON":-8.266666666666667},{"NAME":"Automatic aerosol sampling at the Kohnen Station","TYPE":"Automatic Recording Station","LAT":-75,"LON":0.06666666666666667},{"NAME":"Automatic recording of regional and global seismic activity at the Kohnen Station","TYPE":"Automatic Recording Station","LAT":-75,"LON":0.06666666666666667},{"NAME":"Automatic weather station (AWS) at the Kohnen Station","TYPE":"Automatic Recording Station","LAT":-75.0025,"LON":-0.007222222222222222},{"NAME":"Geophysical Observatory of Neumayer Station III","TYPE":"Automatic Recording Station","LAT":-70.66666666666667,"LON":-8.266666666666667},{"NAME":"Hydroacoustic Observatory (PALAOA)","TYPE":"Automatic Recording Station","LAT":-70.51666666666667,"LON":-8.216666666666667},{"NAME":"Meteorological Observatory of Neumayer Station III","TYPE":"Automatic Recording Station","LAT":-70.66666666666667,"LON":-8.266666666666667}],"color":"#FFCE00","code":"de"}},{"India":{"items":[{"NAME":"Bharati","TYPE":"Station","LAT":-69.4068,"LON":76.19525},{"NAME":"Dakshin Gangotri","TYPE":"Station","LAT":-70.083333,"LON":12},{"NAME":"Maitri","TYPE":"Station","LAT":-70.766834,"LON":11.730783},{"NAME":"Bharati","TYPE":"Automatic Recording Station","LAT":-69.4068,"LON":76.19525},{"NAME":"Maitri Station","TYPE":"Automatic Recording Station","LAT":-70.76444444444445,"LON":11.733333333333333}],"color":"#FF9933","code":"in"}},{"Italy":{"items":[{"NAME":"Concordia","TYPE":"Station","LAT":-75.099975,"LON":123.332605},{"NAME":"Mario Zucchelli","TYPE":"Station","LAT":-74.69480666666666,"LON":164.11326833333334},{"NAME":"Robert Guillard","TYPE":"Station","LAT":-66.687608,"LON":139.90717},{"NAME":"Talos Dome","TYPE":"Camp","LAT":-72.830215,"LON":159.20043166666665},{"NAME":"Browning Pass","TYPE":"Airfield Camp","LAT":-74.622906,"LON":163.91517100000002},{"NAME":"Enigma Lake","TYPE":"Airfield Camp","LAT":-74.719164,"LON":164.027711},{"NAME":"Mid Point","TYPE":"Airfield Camp","LAT":-75.54170333333333,"LON":145.82039833333332},{"NAME":"Sitry Point","TYPE":"Airfield Camp","LAT":-71.65173800000001,"LON":148.654737},{"NAME":"Browning Pass","TYPE":"Automatic Recording Station","LAT":-74.62638888888888,"LON":164.01111111111112},{"NAME":"Cape King","TYPE":"Automatic Recording Station","LAT":-73.58583333333333,"LON":166.6211111111111},{"NAME":"Cape Phillips","TYPE":"Automatic Recording Station","LAT":-73.51833333333333,"LON":169.7486111111111},{"NAME":"Cape Ross","TYPE":"Automatic Recording Station","LAT":-76.715,"LON":162.97},{"NAME":"Concordia Station","TYPE":"Automatic Recording Station","LAT":-75.1,"LON":123.33333333333333},{"NAME":"David Glacier","TYPE":"Automatic Recording Station","LAT":-75.61166666666666,"LON":158.59055555555557},{"NAME":"Edmonson Point","TYPE":"Automatic Recording Station","LAT":-74.33333333333333,"LON":165.13333333333333},{"NAME":"Enigma Lake","TYPE":"Automatic Recording Station","LAT":-74.72500000000001,"LON":164.03305555555556},{"NAME":"Larsen Glacier","TYPE":"Automatic Recording Station","LAT":-74.95055555555555,"LON":161.77055555555557},{"NAME":"Mario Zucchelli Station","TYPE":"Automatic Recording Station","LAT":-74.7,"LON":164.11666666666667},{"NAME":"Mid Point","TYPE":"Automatic Recording Station","LAT":-75.53611111111111,"LON":145.85888888888888},{"NAME":"Priestley Glacier","TYPE":"Automatic Recording Station","LAT":-74.1738888888889,"LON":162.89},{"NAME":"Priestley Névé","TYPE":"Automatic Recording Station","LAT":-73.63916666666667,"LON":160.64555555555555},{"NAME":"Talos Dome","TYPE":"Automatic Recording Station","LAT":-72.76694444444445,"LON":159.0388888888889},{"NAME":"Tourmaline Plateau","TYPE":"Automatic Recording Station","LAT":-74.135,"LON":163.43055555555554}],"color":"#009246","code":"it"}},{"Japan":{"items":[{"NAME":"Asuka","TYPE":"Station","LAT":-71.526273,"LON":24.112516000000003},{"NAME":"Dome Fuji","TYPE":"Station","LAT":-77.317075,"LON":39.698769999999996},{"NAME":"Mizuho","TYPE":"Station","LAT":-77.317075,"LON":39.698769999999996},{"NAME":"Syowa","TYPE":"Station","LAT":-69.004122,"LON":39.581836},{"NAME":"Langhovde Fukuro Ura Refuge","TYPE":"Refuge","LAT":null,"LON":null},{"NAME":"Langhovde Yukidori Zawa Hut","TYPE":"Refuge","LAT":-69.24361111111111,"LON":39.715},{"NAME":"Skallen Refuge","TYPE":"Refuge","LAT":-69.67361111111111,"LON":39.400555555555556},{"NAME":"Skarvsnes Kizahashi Hama Hut","TYPE":"Refuge","LAT":-69.46666666666667,"LON":39.6},{"NAME":"Dome Fuji II Camp","TYPE":"Camp","LAT":-77.3611111111111,"LON":39.64388888888889},{"NAME":"S17 Camp","TYPE":"Camp","LAT":-69.028076,"LON":40.092449},{"NAME":"IGS Tracking Site at Syowa Station (SYOG)","TYPE":"Automatic Recording Station","LAT":-69.00694444444444,"LON":39.58361111111111},{"NAME":"Amundsen Bay","TYPE":"Automatic Recording Station","LAT":-66.79555555555555,"LON":50.577222222222225},{"NAME":"Amundsen Bay","TYPE":"Automatic Recording Station","LAT":-66.79555555555555,"LON":50.578611111111115},{"NAME":"Dome Fuji","TYPE":"Automatic Recording Station","LAT":-77.31666666666666,"LON":39.70305555555556},{"NAME":"H128","TYPE":"Automatic Recording Station","LAT":-69.40138888888889,"LON":41.54472222222222},{"NAME":"H68","TYPE":"Automatic Recording Station","LAT":-69.19222222222223,"LON":41.05027777777777},{"NAME":"Innhovde","TYPE":"Automatic Recording Station","LAT":-69.85583333333332,"LON":37.10861111111111},{"NAME":"JASE2007 (DK379)","TYPE":"Automatic Recording Station","LAT":-75.88805555555557,"LON":25.83361111111111},{"NAME":"Langhovde","TYPE":"Automatic Recording Station","LAT":-69.24305555555556,"LON":39.71472222222223},{"NAME":"Langhovde","TYPE":"Automatic Recording Station","LAT":-69.25,"LON":39.71666666666667},{"NAME":"MD78 (MD78)","TYPE":"Automatic Recording Station","LAT":-71.44861111111112,"LON":-44.00888888888889},{"NAME":"Mizuho","TYPE":"Automatic Recording Station","LAT":-70.7,"LON":44.28916666666667},{"NAME":"Mizuho","TYPE":"Automatic Recording Station","LAT":-70.70166666666667,"LON":44.27972222222222},{"NAME":"New Dome Fuji","TYPE":"Automatic Recording Station","LAT":-77.78888888888889,"LON":39.052499999999995},{"NAME":"New Relay Point (MD364)","TYPE":"Automatic Recording Station","LAT":-74.03,"LON":43},{"NAME":"Oyako Ike","TYPE":"Automatic Recording Station","LAT":-69.47361111111111,"LON":39.611111111111114},{"NAME":"Relay Point (MD364)","TYPE":"Automatic Recording Station","LAT":-74.01027777777777,"LON":42.99166666666667},{"NAME":"Relay Point (MD364)","TYPE":"Automatic Recording Station","LAT":-74.00805555555556,"LON":42.99666666666667},{"NAME":"Skallen","TYPE":"Automatic Recording Station","LAT":-69.6725,"LON":39.401944444444446},{"NAME":"Skallen Oike","TYPE":"Automatic Recording Station","LAT":-69.6738888888889,"LON":39.40416666666667},{"NAME":"Yukidori Zawa","TYPE":"Automatic Recording Station","LAT":-69.24166666666667,"LON":39.739444444444445}],"color":"#BC002D","code":"jp"}},{"Korea (ROK)":{"items":[{"NAME":"Jang Bogo","TYPE":"Station","LAT":-74.62333299999999,"LON":164.20000000000002},{"NAME":"King Sejong","TYPE":"Station","LAT":-62.2275,"LON":-58.78861111111111},{"NAME":"Jang Bogo","TYPE":"Automatic Recording Station","LAT":-74.62333299999999,"LON":164.20000000000002},{"NAME":"King Sejong","TYPE":"Automatic Recording Station","LAT":-62.2275,"LON":-58.78861111111111}],"color":"#C60C30","code":"kr"}},{"Netherlands":{"items":[{"NAME":"Dirck Gerritsz Laboratory","TYPE":"Laboratory","LAT":-67.568636,"LON":-68.124377},{"NAME":"AWS 11, Halvfarryggen","TYPE":"Automatic Recording Station","LAT":-71.16666666666667,"LON":-6.8},{"NAME":"AWS 12, Plateau station B","TYPE":"Automatic Recording Station","LAT":-78.65,"LON":35.63333333333333},{"NAME":"AWS 13, Pole of Inaccessibility","TYPE":"Automatic Recording Station","LAT":-82.11666666666666,"LON":55.03333333333333},{"NAME":"AWS 14, Larsen C North","TYPE":"Automatic Recording Station","LAT":-67.01666666666667,"LON":-61.5},{"NAME":"AWS 15, Larsen C South","TYPE":"Automatic Recording Station","LAT":-67.56666666666666,"LON":-62.15},{"NAME":"AWS 16, Princess Elisabeth","TYPE":"Automatic Recording Station","LAT":-71.95,"LON":23.333333333333332},{"NAME":"AWS 17, Scar Inlet","TYPE":"Automatic Recording Station","LAT":-65.93333333333334,"LON":-61.85},{"NAME":"AWS 9, Kohnen","TYPE":"Automatic Recording Station","LAT":-75,"LON":0}],"color":"#21468B","code":"nl"}},{"New Zealand":{"items":[{"NAME":"Scott Base","TYPE":"Station","LAT":-77.84943666666666,"LON":166.7672816666667},{"NAME":"Cape Royds Hut","TYPE":"Refuge","LAT":-77.54333333333334,"LON":166.1436111111111},{"NAME":"Lower Wright Hut","TYPE":"Refuge","LAT":-77.51666666666667,"LON":161.83333333333334},{"NAME":"Bratina Island Hut","TYPE":"Camp","LAT":-78.01666666666667,"LON":165.53333333333333},{"NAME":"Cape Adare Hut","TYPE":"Camp","LAT":-71.311111,"LON":-170.194444},{"NAME":"Cape Bird Hut","TYPE":"Camp","LAT":-77.21833333333333,"LON":166.4361111111111},{"NAME":"Cape Evans Hut","TYPE":"Camp","LAT":-77.63833333333334,"LON":166.40694444444446},{"NAME":"Cape Roberts Hut","TYPE":"Camp","LAT":-77.03333333333333,"LON":163.2},{"NAME":"Lake Vanda Hut/Facilities Zone","TYPE":"Camp","LAT":-77.51666666666667,"LON":161.83333333333334},{"NAME":"Arrival Heights","TYPE":"Automatic Recording Station","LAT":-77.81666666666666,"LON":166.65},{"NAME":"Scott Base","TYPE":"Automatic Recording Station","LAT":-77.83333333333333,"LON":166.75}],"color":"#00247D","code":"nz"}},{"Norway":{"items":[{"NAME":"Troll Station","TYPE":"Station","LAT":-72.011944,"LON":2.5330559999999998},{"NAME":"Tor","TYPE":"Refuge","LAT":-71.889515,"LON":5.159893333333334},{"NAME":"Troll Airfield","TYPE":"Automatic Recording Station","LAT":-71.95083333333334,"LON":2.466666666666667},{"NAME":"Troll Station","TYPE":"Automatic Recording Station","LAT":-72.011944,"LON":2.5330559999999998},{"NAME":"Trollhaugen","TYPE":"Automatic Recording Station","LAT":-72.01166666666667,"LON":2.5349999999999997}],"color":"#ED2939","code":"no"}},{"Peru":{"items":[{"NAME":"Machu Picchu","TYPE":"Station","LAT":-62.091593,"LON":-58.470559}],"color":"#D91023","code":"pe"}},{"Poland":{"items":[{"NAME":"Dobrowolski Station","TYPE":"Station","LAT":-66.26666666666667,"LON":100.73333333333333},{"NAME":"Henryk Arctowski","TYPE":"Station","LAT":-62.159773,"LON":-58.473322},{"NAME":"Demay","TYPE":"Refuge","LAT":-62.21666666666667,"LON":-58.44166666666666},{"NAME":"Lions Rump","TYPE":"Refuge","LAT":null,"LON":null},{"NAME":"Arctowski Station","TYPE":"Automatic Recording Station","LAT":-62.1625,"LON":-58.46666666666667},{"NAME":"Hennequin, Point","TYPE":"Automatic Recording Station","LAT":-62.13333333333333,"LON":-58.4},{"NAME":"Lions Rump","TYPE":"Automatic Recording Station","LAT":-62.13333333333333,"LON":-58.11666666666667}],"color":"#DC143C","code":"pl"}},{"Romania":{"items":[{"NAME":"Law Racovita","TYPE":"Station","LAT":-69.38829600000001,"LON":76.380696}],"color":"#FCD116","code":"ro"}},{"Russian Federation":{"items":[{"NAME":"Bellingshausen","TYPE":"Station","LAT":-62.198184,"LON":-58.960609000000005},{"NAME":"Bunger Oasis","TYPE":"Station","LAT":-66.26666666666667,"LON":100.73333333333333},{"NAME":"Druzhnaya IV","TYPE":"Station","LAT":-69.74782666666667,"LON":73.70921333333334},{"NAME":"Leningradskaya","TYPE":"Station","LAT":-69.501496,"LON":159.391148},{"NAME":"Mirny","TYPE":"Station","LAT":-66.55318166666666,"LON":93.00955833333333},{"NAME":"Molodezhnaya","TYPE":"Station","LAT":-67.66544333333334,"LON":45.842038333333335},{"NAME":"Novolazarevskaya","TYPE":"Station","LAT":-70.77579666666666,"LON":11.832151666666666},{"NAME":"Progress","TYPE":"Station","LAT":-69.37795,"LON":76.388056},{"NAME":"Progress 3","TYPE":"Station","LAT":-69.41227500000001,"LON":76.40353833333334},{"NAME":"Russkaya","TYPE":"Station","LAT":-74.76572666666667,"LON":-136.80007166666667},{"NAME":"Soyuz","TYPE":"Station","LAT":-70.65,"LON":68.8},{"NAME":"Vostok","TYPE":"Station","LAT":-78.46418166666668,"LON":106.83688166666666},{"NAME":"Druzhnaya-4","TYPE":"Automatic Recording Station","LAT":-69.73333333333333,"LON":73.71666666666667},{"NAME":"Leningradskaya","TYPE":"Automatic Recording Station","LAT":-69.50194444444445,"LON":159.38694444444442},{"NAME":"Molodezhnaya","TYPE":"Automatic Recording Station","LAT":-67.66611111111112,"LON":45.85166666666667},{"NAME":"Russkaya","TYPE":"Automatic Recording Station","LAT":-74.76583333333333,"LON":-136.79888888888888}],"color":"#D52B1E","code":"ru"}},{"South Africa":{"items":[{"NAME":"SANAE IV","TYPE":"Station","LAT":-71.67361111111111,"LON":-2.828611111111111},{"NAME":"SANAP Summer Station","TYPE":"Station","LAT":-70.64999700000001,"LON":-8.249998999999999}],"color":"#006233","code":"za"}},{"Spain":{"items":[{"NAME":"Gabriel de Castilla Station","TYPE":"Station","LAT":-62.97719666666667,"LON":-60.675745},{"NAME":"Juan Carlos I","TYPE":"Station","LAT":-62.66305555555555,"LON":-60.38886111111111},{"NAME":"International Field Camp Peninsula Byers","TYPE":"Camp","LAT":-62.57638888888889,"LON":-61.218611111111116},{"NAME":"Gabriel de Castilla Station","TYPE":"Automatic Recording Station","LAT":-62.97719666666667,"LON":-60.675745},{"NAME":"Johnsons, Glaciar","TYPE":"Automatic Recording Station","LAT":-62.665,"LON":-60.35},{"NAME":"Juan Carlos I","TYPE":"Automatic Recording Station","LAT":-62.66305555555555,"LON":-60.38886111111111},{"NAME":"Lago Somero, Peninsula Byers","TYPE":"Automatic Recording Station","LAT":-62.64722222222222,"LON":-61.11027777777778}],"color":"#F1BF00","code":"es"}},{"Sweden":{"items":[{"NAME":"Svea","TYPE":"Station","LAT":-74.58333333333333,"LON":-11.216666666666667},{"NAME":"Wasa","TYPE":"Station","LAT":-73.042778,"LON":-13.412778000000001}],"color":"#006AA7","code":"se"}},{"Switzerland":{"items":{},"color":"#FF0000","code":"ch"}},{"Türkiye":{"items":[{"NAME":"Dismal Island","TYPE":"Automatic Recording Station","LAT":-68.096175,"LON":-68.8699861111111},{"NAME":"Horseshoe Island","TYPE":"Automatic Recording Station","LAT":-67.83,"LON":-67.23833333333333}],"color":"#E30A17","code":"tr"}},{"Ukraine":{"items":[{"NAME":"Vernadsky","TYPE":"Station","LAT":-65.25,"LON":-64.26666666666667},{"NAME":"Vernadsky","TYPE":"Automatic Recording Station","LAT":-65.25,"LON":-64.26666666666667}],"color":"#FFD500","code":"ua"}},{"United Kingdom":{"items":[{"NAME":"Damoy (HSM 84)","TYPE":"Station","LAT":-64.81666666666666,"LON":-63.5},{"NAME":"Detaille Island (HSM 83)","TYPE":"Station","LAT":-66.86666666666666,"LON":-66.8},{"NAME":"Halley VI","TYPE":"Station","LAT":-75.58333333333333,"LON":-26.233333333333334},{"NAME":"Horseshoe Island (HSM 63)","TYPE":"Station","LAT":-67.8,"LON":-67.28333333333333},{"NAME":"Port Lockroy","TYPE":"Station","LAT":-64.825,"LON":-63.49333333333333},{"NAME":"Rothera","TYPE":"Station","LAT":-67.5675,"LON":-68.12972222222221},{"NAME":"Signy","TYPE":"Station","LAT":-60.708333333333336,"LON":-45.595},{"NAME":"Stonington Island (HSM 64)","TYPE":"Station","LAT":-68.18333333333334,"LON":-67},{"NAME":"Wordie House (HSM 62)","TYPE":"Station","LAT":-65.25,"LON":-64.26666666666667},{"NAME":"Cummings","TYPE":"Refuge","LAT":-60.72361111111111,"LON":-45.666666666666664},{"NAME":"Foca","TYPE":"Refuge","LAT":-60.69583333333333,"LON":-45.64416666666666},{"NAME":"Gourlay","TYPE":"Refuge","LAT":-60.73222222222223,"LON":-45.581388888888895},{"NAME":"Lagoon Island","TYPE":"Refuge","LAT":-67.59444444444443,"LON":-68.23611111111111},{"NAME":"Station C - Cape Geddes","TYPE":"Refuge","LAT":-60.68333333333333,"LON":-44.56666666666667},{"NAME":"Waterpipe","TYPE":"Refuge","LAT":-60.7,"LON":-45.608333333333334},{"NAME":"Dirck Gerritsz Laboratory","TYPE":"Laboratory","LAT":-67.568636,"LON":-68.124377},{"NAME":"Fossil Bluff","TYPE":"Depot","LAT":-71.33333333333333,"LON":-68.27777777777777},{"NAME":"Sky Blu","TYPE":"Depot","LAT":-74.84888888888888,"LON":-71.57249999999999},{"NAME":"Halley VI","TYPE":"Automatic Recording Station","LAT":-75.58333333333333,"LON":-26.233333333333334},{"NAME":"Rothera","TYPE":"Automatic Recording Station","LAT":-67.5675,"LON":-68.12972222222221},{"NAME":"Signy","TYPE":"Automatic Recording Station","LAT":-60.708333333333336,"LON":-45.595}],"color":"#CF142B","code":"gb"}},{"United States":{"items":[{"NAME":"Amundsen-Scott South Pole","TYPE":"Station","LAT":-89.9975,"LON":139.27280000000002},{"NAME":"McMurdo","TYPE":"Station","LAT":-77.85,"LON":166.66666666666666},{"NAME":"Palmer","TYPE":"Station","LAT":-64.774261,"LON":-64.05305666666666},{"NAME":"CTAM","TYPE":"Depot","LAT":-84.006544,"LON":164.402997},{"NAME":"Marble Point Refueling Facility","TYPE":"Depot","LAT":-77.43331666666667,"LON":163.83333},{"NAME":"Black Island Camp","TYPE":"Camp","LAT":-78.13333333333334,"LON":166.15},{"NAME":"Bull Pass (McM DV)","TYPE":"Camp","LAT":-77.51694444444445,"LON":161.8513888888889},{"NAME":"Byrd Surface","TYPE":"Camp","LAT":-80.01666666666667,"LON":-119.53333333333333},{"NAME":"Cape Crozier","TYPE":"Camp","LAT":-77.5,"LON":169.66666666666666},{"NAME":"Cape Royds Camp","TYPE":"Camp","LAT":-77.55,"LON":166.13333333333333},{"NAME":"Cape Shirreff Camp","TYPE":"Camp","LAT":-62.47,"LON":-60.771388888888886},{"NAME":"Copacabana, King George Island","TYPE":"Camp","LAT":-62.166666666666664,"LON":-58.46666666666667},{"NAME":"F6 Camp","TYPE":"Camp","LAT":-77.60833333333333,"LON":163.25555555555556},{"NAME":"Lake Bonney Camp","TYPE":"Camp","LAT":-77.7,"LON":162.45},{"NAME":"Lake Fryxell","TYPE":"Camp","LAT":-77.6,"LON":163.11666666666667},{"NAME":"Lake Hoare","TYPE":"Camp","LAT":-77.62277777777777,"LON":162.90277777777777},{"NAME":"Lower Erebus Hut and Cache","TYPE":"Camp","LAT":-77.5,"LON":167.16666666666666},{"NAME":"Lower Wright Hut","TYPE":"Camp","LAT":-77.44250000000001,"LON":162.65},{"NAME":"Mt Newall Repeater Station","TYPE":"Camp","LAT":-77.50444444444445,"LON":162.625},{"NAME":"New Harbor Camp","TYPE":"Camp","LAT":-77.57777777777777,"LON":163.51944444444445},{"NAME":"Pine Island Glacier Helo Facility","TYPE":"Camp","LAT":-75.80361111111111,"LON":-100.27722222222222},{"NAME":"Shackleton Glacier Camp","TYPE":"Camp","LAT":-85.086232,"LON":-175.289469},{"NAME":"Siple Dome","TYPE":"Camp","LAT":-81.66666666666667,"LON":-149.01666666666668},{"NAME":"WAIS Divide","TYPE":"Camp","LAT":-79.48333333333333,"LON":-112.08333333333333},{"NAME":"Odell Glacier","TYPE":"Airfield Camp","LAT":-76.65,"LON":159.9666},{"NAME":"AGO 1 (Automatic Geophysical Observatories)","TYPE":"Automatic Recording Station","LAT":-83.86,"LON":129.60999999999999},{"NAME":"AGO-2 (Automated Geophysical Observatories)","TYPE":"Automatic Recording Station","LAT":-85.67,"LON":13.620000000000001},{"NAME":"AGO-3 (Automated Geophysical Observatories)","TYPE":"Automatic Recording Station","LAT":-82.75,"LON":28.59},{"NAME":"AGO-4","TYPE":"Automatic Recording Station","LAT":-80.01,"LON":96.76},{"NAME":"AGO-5 (Automatic Geophysical Observatories)","TYPE":"Automatic Recording Station","LAT":-77.24,"LON":123.52},{"NAME":"AGO-6 (Automatic Geophysical Observations)","TYPE":"Automatic Recording Station","LAT":-69.5,"LON":130.01666666666668},{"NAME":"Alexander's Tall Tower","TYPE":"Automatic Recording Station","LAT":-78,"LON":170},{"NAME":"Antarctica","TYPE":"Automatic Recording Station","LAT":-90,"LON":0},{"NAME":"Beacon Valley","TYPE":"Automatic Recording Station","LAT":-77.81666666666666,"LON":160.65},{"NAME":"Beacon Valley (Main site)","TYPE":"Automatic Recording Station","LAT":-77.87416666666665,"LON":160.53861111111112},{"NAME":"Beacon Valley, Central","TYPE":"Automatic Recording Station","LAT":-77.80333333333333,"LON":160},{"NAME":"Beacon Valley, Lower","TYPE":"Automatic Recording Station","LAT":-77.84861111111111,"LON":160.60194444444443},{"NAME":"Biesiada Crevasse Field (AWS\n108)","TYPE":"Automatic Recording Station","LAT":-77.90666666666667,"LON":169.25277777777777},{"NAME":"Bonaparte Point","TYPE":"Automatic Recording Station","LAT":-64.78333333333333,"LON":-64.08333333333333},{"NAME":"Butter Point-Ferrar (AWS 105)","TYPE":"Automatic Recording Station","LAT":-77.70611111111111,"LON":163.90277777777777},{"NAME":"Byrd Surface","TYPE":"Automatic Recording Station","LAT":-80.01666666666667,"LON":-119.53333333333333},{"NAME":"Canada Glacier","TYPE":"Automatic Recording Station","LAT":-77.61666666666666,"LON":162.98333333333332},{"NAME":"Canada Glacier, Upper","TYPE":"Automatic Recording Station","LAT":-77.61277777777777,"LON":162.9636111111111},{"NAME":"Cape Bird","TYPE":"Automatic Recording Station","LAT":-77,"LON":166},{"NAME":"Cape Crozier","TYPE":"Automatic Recording Station","LAT":-77.5,"LON":168},{"NAME":"Cape Denison","TYPE":"Automatic Recording Station","LAT":-67,"LON":142.66666666666666},{"NAME":"Cape Hallett","TYPE":"Automatic Recording Station","LAT":-72.31666666666666,"LON":170.26666666666668},{"NAME":"Cape Royds (AWS 106)","TYPE":"Automatic Recording Station","LAT":-77.545,"LON":166},{"NAME":"Cape Spencer (AWS 111)","TYPE":"Automatic Recording Station","LAT":-77.96694444444445,"LON":167.525},{"NAME":"Commonwealth Glacier","TYPE":"Automatic Recording Station","LAT":-77.58333333333333,"LON":163.31666666666666},{"NAME":"D-10","TYPE":"Automatic Recording Station","LAT":-66.71000000000001,"LON":139.82999999999998},{"NAME":"D-47","TYPE":"Automatic Recording Station","LAT":-67.4,"LON":138.73},{"NAME":"Dismal Island","TYPE":"Automatic Recording Station","LAT":-68.1,"LON":-68.83333333333333},{"NAME":"Dome C II","TYPE":"Automatic Recording Station","LAT":-75.11999999999999,"LON":123.36999999999999},{"NAME":"Dome Fuji","TYPE":"Automatic Recording Station","LAT":-77.31666666666666,"LON":39.70305555555556},{"NAME":"Elaine","TYPE":"Automatic Recording Station","LAT":-83.05666666666666,"LON":174.21833333333333},{"NAME":"Emilia","TYPE":"Automatic Recording Station","LAT":-78.38222222222221,"LON":173.21944444444443},{"NAME":"Emma","TYPE":"Automatic Recording Station","LAT":-84,"LON":175},{"NAME":"Erin","TYPE":"Automatic Recording Station","LAT":-84,"LON":-128},{"NAME":"F6","TYPE":"Automatic Recording Station","LAT":-77.60777777777777,"LON":163.2511111111111},{"NAME":"Farnell Valley","TYPE":"Automatic Recording Station","LAT":-77.88333333333334,"LON":160.65},{"NAME":"Ferrell II","TYPE":"Automatic Recording Station","LAT":-77,"LON":170},{"NAME":"Ford Rock (AWS 103)","TYPE":"Automatic Recording Station","LAT":-77.76166666666667,"LON":166},{"NAME":"Gill","TYPE":"Automatic Recording Station","LAT":-79,"LON":178},{"NAME":"Gossler Islands","TYPE":"Automatic Recording Station","LAT":-64.7,"LON":-64.36666666666666},{"NAME":"Henry","TYPE":"Automatic Recording Station","LAT":-89,"LON":102},{"NAME":"Herbie Alley North (AWS100)","TYPE":"Automatic Recording Station","LAT":-78.09055555555555,"LON":166.68055555555554},{"NAME":"Hjorth Hill","TYPE":"Automatic Recording Station","LAT":-77.51666666666667,"LON":163.61666666666667},{"NAME":"Hobo Station 1","TYPE":"Automatic Recording Station","LAT":-77.4725,"LON":161.49638888888887},{"NAME":"Hobo Station 2","TYPE":"Automatic Recording Station","LAT":-77.46527777777779,"LON":161.33083333333332},{"NAME":"Howard Glacier","TYPE":"Automatic Recording Station","LAT":-77.66666666666667,"LON":163.08333333333334},{"NAME":"Howard Glacier, Upper","TYPE":"Automatic Recording Station","LAT":-77,"LON":163.14527777777778},{"NAME":"Hughes Glacier","TYPE":"Automatic Recording Station","LAT":-77.73333333333333,"LON":162.45},{"NAME":"Janet","TYPE":"Automatic Recording Station","LAT":-77.17361111111111,"LON":-123.39250000000001},{"NAME":"Joubins Island 1","TYPE":"Automatic Recording Station","LAT":-64.91805555555555,"LON":-64.0436111111111},{"NAME":"Joubins Island 2","TYPE":"Automatic Recording Station","LAT":-64.7875,"LON":-64.365},{"NAME":"Jules (AWS 113)","TYPE":"Automatic Recording Station","LAT":-77.87527777777777,"LON":165.29916666666668},{"NAME":"Kirkwood Islands","TYPE":"Automatic Recording Station","LAT":-68.36666666666666,"LON":-69},{"NAME":"Lake Bonney 1","TYPE":"Automatic Recording Station","LAT":-77.71444444444445,"LON":162.43416666666667},{"NAME":"Lake Bonney 2","TYPE":"Automatic Recording Station","LAT":-77.71472222222222,"LON":162.4647222222222},{"NAME":"Lake Brownworth","TYPE":"Automatic Recording Station","LAT":-77.43361111111112,"LON":162.7036111111111},{"NAME":"Lake Fryxell","TYPE":"Automatic Recording Station","LAT":-77.6,"LON":163.11666666666667},{"NAME":"Lake Hoare 1","TYPE":"Automatic Recording Station","LAT":-77.62527777777777,"LON":162.90027777777777},{"NAME":"Lake Hoare 2","TYPE":"Automatic Recording Station","LAT":-77.62527777777777,"LON":162.90055555555557},{"NAME":"Lake Hoare 3","TYPE":"Automatic Recording Station","LAT":-77.62416666666665,"LON":162.89888888888888},{"NAME":"Lake Joyce","TYPE":"Automatic Recording Station","LAT":-77.71944444444445,"LON":161.5977777777778},{"NAME":"Lake Miers","TYPE":"Automatic Recording Station","LAT":-78.10111111111111,"LON":163.78777777777776},{"NAME":"Lake Vanda 1","TYPE":"Automatic Recording Station","LAT":-77.51666666666667,"LON":161.66666666666666},{"NAME":"Lake Vanda 2","TYPE":"Automatic Recording Station","LAT":-77.52555555555556,"LON":161.6913888888889},{"NAME":"Lake Vida","TYPE":"Automatic Recording Station","LAT":-77.38333333333334,"LON":161.91666666666666},{"NAME":"Laurie II","TYPE":"Automatic Recording Station","LAT":-77.45194444444445,"LON":170.76611111111112},{"NAME":"Lettau","TYPE":"Automatic Recording Station","LAT":-82.52,"LON":174.45},{"NAME":"Linda","TYPE":"Automatic Recording Station","LAT":-78.48,"LON":168.38},{"NAME":"Lorne","TYPE":"Automatic Recording Station","LAT":-78,"LON":170},{"NAME":"Lorne (Meeley)","TYPE":"Automatic Recording Station","LAT":-78.45,"LON":170},{"NAME":"Manuela","TYPE":"Automatic Recording Station","LAT":-74.95,"LON":163.69},{"NAME":"Marble Point (AWS 301)","TYPE":"Automatic Recording Station","LAT":-77.36666666666666,"LON":163.36666666666667},{"NAME":"Marble Point II","TYPE":"Automatic Recording Station","LAT":-77,"LON":163},{"NAME":"Margaret","TYPE":"Automatic Recording Station","LAT":-80,"LON":165},{"NAME":"Marilyn","TYPE":"Automatic Recording Station","LAT":-79.89750000000001,"LON":165.85611111111112},{"NAME":"Miers Valley 1","TYPE":"Automatic Recording Station","LAT":-78.10111111111111,"LON":163.7875},{"NAME":"Miers Valley 2","TYPE":"Automatic Recording Station","LAT":-77,"LON":162},{"NAME":"Minna Bluff","TYPE":"Automatic Recording Station","LAT":-78.51666666666667,"LON":166.41666666666666},{"NAME":"Mizuho","TYPE":"Automatic Recording Station","LAT":-70.7,"LON":44.29},{"NAME":"Moraine Canyon","TYPE":"Automatic Recording Station","LAT":-86.15,"LON":-157.5},{"NAME":"Mt Electra","TYPE":"Automatic Recording Station","LAT":-77.51027777777777,"LON":160.845},{"NAME":"Mt Erebus, (AWS 114)","TYPE":"Automatic Recording Station","LAT":-77.53444444444445,"LON":167.08555555555557},{"NAME":"Mt Fleming","TYPE":"Automatic Recording Station","LAT":-77.5325,"LON":160.2711111111111},{"NAME":"Mt Friis","TYPE":"Automatic Recording Station","LAT":-77.53,"LON":160.28},{"NAME":"Mt Friis (Friis Hills)","TYPE":"Automatic Recording Station","LAT":-77.7475,"LON":161.51611111111112},{"NAME":"Mullins Valley","TYPE":"Automatic Recording Station","LAT":-77.9,"LON":160.58333333333334},{"NAME":"New Harbor (Explorer's Cove)","TYPE":"Automatic Recording Station","LAT":-77.5886111111111,"LON":163.4175},{"NAME":"Nico","TYPE":"Automatic Recording Station","LAT":-89,"LON":89.67},{"NAME":"None Listed 1","TYPE":"Automatic Recording Station","LAT":-75,"LON":-87.47},{"NAME":"None Listed 2","TYPE":"Automatic Recording Station","LAT":-77,"LON":-972},{"NAME":"Norsel Point","TYPE":"Automatic Recording Station","LAT":-64.76666666666667,"LON":-64.1},{"NAME":"North Crevasse (AWS 104)","TYPE":"Automatic Recording Station","LAT":-77.86222222222221,"LON":168},{"NAME":"North Fork","TYPE":"Automatic Recording Station","LAT":-77.53333333333333,"LON":161.25},{"NAME":"Ong Valley","TYPE":"Automatic Recording Station","LAT":-83.23333333333333,"LON":157.61666666666667},{"NAME":"Pegasus Ice Runway (AWS\n150)","TYPE":"Automatic Recording Station","LAT":-77.95583333333333,"LON":166.50944444444445},{"NAME":"Phoenix Airfield","TYPE":"Automatic Recording Station","LAT":-77,"LON":166},{"NAME":"Pine Island Glacier","TYPE":"Automatic Recording Station","LAT":-75.16666666666667,"LON":-100},{"NAME":"Pine Island Glacier Helo Camp","TYPE":"Automatic Recording Station","LAT":-75.5,"LON":-100},{"NAME":"Port Martin","TYPE":"Automatic Recording Station","LAT":-66.82,"LON":141.4},{"NAME":"Possession Island","TYPE":"Automatic Recording Station","LAT":-71.86666666666666,"LON":171.2},{"NAME":"Queer Mountain","TYPE":"Automatic Recording Station","LAT":-77.13333333333334,"LON":161.75},{"NAME":"Relay Station","TYPE":"Automatic Recording Station","LAT":-74.02,"LON":43.059999999999995},{"NAME":"Rhone Glacier","TYPE":"Automatic Recording Station","LAT":-77.7,"LON":162.23333333333332},{"NAME":"Rhone Platform","TYPE":"Automatic Recording Station","LAT":-77.70611111111111,"LON":162.13777777777776},{"NAME":"Ridge A","TYPE":"Automatic Recording Station","LAT":-81.67361111111111,"LON":72.71611111111112},{"NAME":"Sabrina","TYPE":"Automatic Recording Station","LAT":-84.25,"LON":170},{"NAME":"Schwerdtfeger","TYPE":"Automatic Recording Station","LAT":-79,"LON":170},{"NAME":"Schwerdtfeger, Skomik","TYPE":"Automatic Recording Station","LAT":-79,"LON":170},{"NAME":"SOUTH POLE 50k","TYPE":"Automatic Recording Station","LAT":-89.83999999999999,"LON":137.04},{"NAME":"Taylor Glacier","TYPE":"Automatic Recording Station","LAT":-77.73333333333333,"LON":162.16666666666666},{"NAME":"Taylor Glacier MET1","TYPE":"Automatic Recording Station","LAT":-77.75722222222223,"LON":161.7777777777778},{"NAME":"Taylor Glacier MET1(2)","TYPE":"Automatic Recording Station","LAT":-77.83944444444444,"LON":161.5525},{"NAME":"Taylor Glacier MET2","TYPE":"Automatic Recording Station","LAT":-77.83388888888888,"LON":161.21777777777777},{"NAME":"Taylor Glacier MET3","TYPE":"Automatic Recording Station","LAT":-77.83916666666666,"LON":161.5575},{"NAME":"Taylor Glacier MET4","TYPE":"Automatic Recording Station","LAT":-77.71777777777778,"LON":160},{"NAME":"Taylor Glacier MET6","TYPE":"Automatic Recording Station","LAT":-77.87055555555555,"LON":161.36666666666667},{"NAME":"University Valley  1","TYPE":"Automatic Recording Station","LAT":-77.70861111111111,"LON":161.5991666666667},{"NAME":"Unnamed","TYPE":"Automatic Recording Station","LAT":-77,"LON":163},{"NAME":"Victoria Valley, Upper","TYPE":"Automatic Recording Station","LAT":-77,"LON":161},{"NAME":"Vito","TYPE":"Automatic Recording Station","LAT":-78,"LON":177},{"NAME":"WAIS Divide","TYPE":"Automatic Recording Station","LAT":-79.48333333333333,"LON":-112.08333333333333},{"NAME":"Wauwerman Islands","TYPE":"Automatic Recording Station","LAT":-64,"LON":-64.0436111111111},{"NAME":"White Is. (AWS 109)","TYPE":"Automatic Recording Station","LAT":-78.12416666666665,"LON":168.32},{"NAME":"White Island","TYPE":"Automatic Recording Station","LAT":-66.73333333333333,"LON":48.583333333333336},{"NAME":"Whiteout (AWS 110)","TYPE":"Automatic Recording Station","LAT":-77.84777777777778,"LON":167.14666666666665},{"NAME":"Whitlock","TYPE":"Automatic Recording Station","LAT":-76.14,"LON":168.39},{"NAME":"Williams Field","TYPE":"Automatic Recording Station","LAT":-77.86833333333333,"LON":166.8983333333333},{"NAME":"Williams Field LDB Camp","TYPE":"Automatic Recording Station","LAT":-77.86333333333333,"LON":167.0627777777778},{"NAME":"Williams Field, Sarah","TYPE":"Automatic Recording Station","LAT":-77.86833333333333,"LON":166.8983333333333},{"NAME":"Windless Bight","TYPE":"Automatic Recording Station","LAT":-77.7,"LON":167.66666666666666},{"NAME":"Wright Valley","TYPE":"Automatic Recording Station","LAT":-77.51666666666667,"LON":161.83333333333334},{"NAME":"Wright Valley, Upper 1","TYPE":"Automatic Recording Station","LAT":-77,"LON":161.24527777777777},{"NAME":"Wright Valley, Upper 2","TYPE":"Automatic Recording Station","LAT":-77.56333333333333,"LON":161.24916666666667}],"color":"#3C3B6E","code":"us"}},{"Uruguay":{"items":[{"NAME":"Artigas","TYPE":"Station","LAT":-62.184551666666664,"LON":-58.85244166666667},{"NAME":"Ruperto Elichiribehety","TYPE":"Station","LAT":-63.402222,"LON":-56.990833},{"NAME":"Artigas","TYPE":"Automatic Recording Station","LAT":-62.184551666666664,"LON":-58.85244166666667}],"color":"#0038A8","code":"uy"}},{"Venezuela":{"items":[],"color":"#FCD116","code":"ve"}}]